pysdk/__init__.py
pysdk/grvt_ccxt.py
pysdk/grvt_ccxt_base.py
pysdk/grvt_ccxt_env.py
pysdk/grvt_ccxt_logging_selector.py
pysdk/grvt_ccxt_pro.py
pysdk/grvt_ccxt_test_utils.py
pysdk/grvt_ccxt_types.py
pysdk/grvt_ccxt_utils.py
pysdk/grvt_ccxt_ws.py
pysdk/grvt_fixed_types.py
pysdk/grvt_raw_async.py
pysdk/grvt_raw_base.py
pysdk/grvt_raw_env.py
pysdk/grvt_raw_signing.py
pysdk/grvt_raw_sync.py
pysdk/grvt_raw_types.py
grvt_pysdk-0.2.0.dist-info/METADATA
grvt_pysdk-0.2.0.dist-info/WHEEL
grvt_pysdk-0.2.0.dist-info/licenses/LICENSE
grvt_pysdk-0.2.0.dist-info/RECORD
