Metadata-Version: 2.4
Name: grvt-pysdk
Version: 0.2.0
Summary: GRVT Python SDK
Project-URL: homepage, https://github.com/gravity-technologies/grvt-pysdk
Project-URL: repository, https://github.com/gravity-technologies/grvt-pysdk
Author-email: GRVT <contact@grvt.io>
License:                                  Apache License
License-File: LICENSE
Requires-Python: >=3.10
Requires-Dist: aiohttp>=3.10.11
Requires-Dist: backports-weakref>=1.0.post1
Requires-Dist: dacite>=1.8.1
Requires-Dist: dataclasses-json>=0.6.7
Requires-Dist: eth-account>=0.13.4
Requires-Dist: inflection>=0.5.1
Requires-Dist: requests>=2.32.3
Requires-Dist: websockets==13.1
